{
  "tiktok": {
    "videos": [
      {
        "url": "https://www.tiktok.com/@scotland.wtf/video/7566599409178332448",
        "position": 1
      },
      {
        "url": "https://www.tiktok.com/@watchthefall_wtf/video/7524599661609372950",
        "position": 2
      },
      {
        "url": "https://www.tiktok.com/@usa_wtf/video/7540041489225714946",
        "position": 3
      },
      {
        "url": "https://www.tiktok.com/@australiawtf/video/7541408537977621782",
        "position": 4
      },
      {
        "url": "https://www.tiktok.com/@europewtf/video/7532287057226468630",
        "position": 5
      },
      {
        "url": "https://www.tiktok.com/@irelandwtf/video/7526230419101027606",
        "position": 7
      },
      {
        "url": "https://www.tiktok.com/@thewestwtf/video/7499150612475415830",
        "position": 8
      },
      {
        "url": "https://www.tiktok.com/@britainwtf/video/7500168525261049120",
        "position": 10
      }
    ],
    "ad_positions": [6, 9],
    "regional": {
      "scotland": [
        {"url": "https://www.tiktok.com/@scotland.wtf/video/7569539989046824225"},
        {"url": "https://www.tiktok.com/@scotland.wtf/video/7569276595693833504"},
        {"url": "https://www.tiktok.com/@scotland.wtf/video/7569245272555916576"},
        {"url": "https://www.tiktok.com/@scotland.wtf/video/7569165489243508001"},
        {"url": "https://www.tiktok.com/@scotland.wtf/video/7568874052157312289"},
        {"url": "https://www.tiktok.com/@scotland.wtf/video/7568407619241528608"},
        {"url": "https://www.tiktok.com/@scotland.wtf/video/7568550016558566689"},
        {"url": "https://www.tiktok.com/@scotland.wtf/video/7568275688713637142"},
        {"url": "https://www.tiktok.com/@scotland.wtf/video/7568082752294096161"},
        {"url": "https://www.tiktok.com/@scotland.wtf/video/7567668276793183521"},
        {"url": "https://www.tiktok.com/@scotland.wtf/video/7551742300418805014"},
        {"url": "https://www.tiktok.com/@scotland.wtf/video/7545174730572156182"},
        {"url": "https://www.tiktok.com/@scotland.wtf/video/7566599409178332448"}
      ],
      "britain": [
        {"url": "https://www.tiktok.com/@britainwtf/video/7512977977437605142"},
        {"url": "https://www.tiktok.com/@britainwtf/video/7516275708994325782"},
        {"url": "https://www.tiktok.com/@britainwtf/video/7514680292875980054"},
        {"url": "https://www.tiktok.com/@britainwtf/video/7500168525261049120"},
        {"url": "https://www.tiktok.com/@britainwtf/video/7500512844027383073"},
        {"url": "https://www.tiktok.com/@britainwtf/video/7499358669818170646"},
        {"url": "https://www.tiktok.com/@britainwtf/video/7499179250092690720"},
        {"url": "https://www.tiktok.com/@britainwtf/video/placeholder8"},
        {"url": "https://www.tiktok.com/@britainwtf/video/placeholder9"},
        {"url": "https://www.tiktok.com/@britainwtf/video/placeholder10"}
      ],
      "ai": [
        {"url": "https://www.tiktok.com/@ai.wtf/video/7566599409178332448"},
        {"url": "https://www.tiktok.com/@ai.wtf/video/7524599661609372950"},
        {"url": "https://www.tiktok.com/@ai.wtf/video/7540041489225714946"},
        {"url": "https://www.tiktok.com/@ai.wtf/video/7541408537977621782"},
        {"url": "https://www.tiktok.com/@ai.wtf/video/7532287057226468630"},
        {"url": "https://www.tiktok.com/@ai.wtf/video/7526230419101027606"},
        {"url": "https://www.tiktok.com/@ai.wtf/video/7499150612475415830"},
        {"url": "https://www.tiktok.com/@ai.wtf/video/7500168525261049120"},
        {"url": "https://www.tiktok.com/@ai.wtf/video/7566599409178332448"},
        {"url": "https://www.tiktok.com/@ai.wtf/video/7524599661609372950"},
        {"url": "https://www.tiktok.com/@ai.wtf/video/7540041489225714946"},
        {"url": "https://www.tiktok.com/@ai.wtf/video/7541408537977621782"},
        {"url": "https://www.tiktok.com/@ai.wtf/video/7532287057226468630"}
      ],
      "europe": [
        {"url": "https://www.tiktok.com/@europewtf/video/placeholder1"},
        {"url": "https://www.tiktok.com/@europewtf/video/placeholder2"},
        {"url": "https://www.tiktok.com/@europewtf/video/placeholder3"},
        {"url": "https://www.tiktok.com/@europewtf/video/placeholder4"},
        {"url": "https://www.tiktok.com/@europewtf/video/placeholder5"},
        {"url": "https://www.tiktok.com/@europewtf/video/placeholder6"},
        {"url": "https://www.tiktok.com/@europewtf/video/placeholder7"},
        {"url": "https://www.tiktok.com/@europewtf/video/placeholder8"},
        {"url": "https://www.tiktok.com/@europewtf/video/placeholder9"},
        {"url": "https://www.tiktok.com/@europewtf/video/placeholder10"},
        {"url": "https://www.tiktok.com/@europewtf/video/placeholder11"},
        {"url": "https://www.tiktok.com/@europewtf/video/placeholder12"},
        {"url": "https://www.tiktok.com/@europewtf/video/placeholder13"}
      ],
      "england": [
        {"url": "https://www.tiktok.com/@englandwtf/video/placeholder1"},
        {"url": "https://www.tiktok.com/@englandwtf/video/placeholder2"},
        {"url": "https://www.tiktok.com/@englandwtf/video/placeholder3"},
        {"url": "https://www.tiktok.com/@englandwtf/video/placeholder4"},
        {"url": "https://www.tiktok.com/@englandwtf/video/placeholder5"},
        {"url": "https://www.tiktok.com/@englandwtf/video/placeholder6"},
        {"url": "https://www.tiktok.com/@englandwtf/video/placeholder7"},
        {"url": "https://www.tiktok.com/@englandwtf/video/placeholder8"},
        {"url": "https://www.tiktok.com/@englandwtf/video/placeholder9"},
        {"url": "https://www.tiktok.com/@englandwtf/video/placeholder10"},
        {"url": "https://www.tiktok.com/@englandwtf/video/placeholder11"},
        {"url": "https://www.tiktok.com/@englandwtf/video/placeholder12"},
        {"url": "https://www.tiktok.com/@englandwtf/video/placeholder13"}
      ],
      "wales": [
        {"url": "https://www.tiktok.com/@waleswtf/video/placeholder1"},
        {"url": "https://www.tiktok.com/@waleswtf/video/placeholder2"},
        {"url": "https://www.tiktok.com/@waleswtf/video/placeholder3"},
        {"url": "https://www.tiktok.com/@waleswtf/video/placeholder4"},
        {"url": "https://www.tiktok.com/@waleswtf/video/placeholder5"},
        {"url": "https://www.tiktok.com/@waleswtf/video/placeholder6"},
        {"url": "https://www.tiktok.com/@waleswtf/video/placeholder7"},
        {"url": "https://www.tiktok.com/@waleswtf/video/placeholder8"},
        {"url": "https://www.tiktok.com/@waleswtf/video/placeholder9"},
        {"url": "https://www.tiktok.com/@waleswtf/video/placeholder10"},
        {"url": "https://www.tiktok.com/@waleswtf/video/placeholder11"},
        {"url": "https://www.tiktok.com/@waleswtf/video/placeholder12"},
        {"url": "https://www.tiktok.com/@waleswtf/video/placeholder13"}
      ],
      "ireland": [
        {"url": "https://www.tiktok.com/@irelandwtf/video/placeholder1"},
        {"url": "https://www.tiktok.com/@irelandwtf/video/placeholder2"},
        {"url": "https://www.tiktok.com/@irelandwtf/video/placeholder3"},
        {"url": "https://www.tiktok.com/@irelandwtf/video/placeholder4"},
        {"url": "https://www.tiktok.com/@irelandwtf/video/placeholder5"},
        {"url": "https://www.tiktok.com/@irelandwtf/video/placeholder6"},
        {"url": "https://www.tiktok.com/@irelandwtf/video/placeholder7"},
        {"url": "https://www.tiktok.com/@irelandwtf/video/placeholder8"},
        {"url": "https://www.tiktok.com/@irelandwtf/video/placeholder9"},
        {"url": "https://www.tiktok.com/@irelandwtf/video/placeholder10"},
        {"url": "https://www.tiktok.com/@irelandwtf/video/placeholder11"},
        {"url": "https://www.tiktok.com/@irelandwtf/video/placeholder12"},
        {"url": "https://www.tiktok.com/@irelandwtf/video/placeholder13"}
      ],
      "france": [
        {"url": "https://www.tiktok.com/@francewtf/video/placeholder1"},
        {"url": "https://www.tiktok.com/@francewtf/video/placeholder2"},
        {"url": "https://www.tiktok.com/@francewtf/video/placeholder3"},
        {"url": "https://www.tiktok.com/@francewtf/video/placeholder4"},
        {"url": "https://www.tiktok.com/@francewtf/video/placeholder5"},
        {"url": "https://www.tiktok.com/@francewtf/video/placeholder6"},
        {"url": "https://www.tiktok.com/@francewtf/video/placeholder7"},
        {"url": "https://www.tiktok.com/@francewtf/video/placeholder8"},
        {"url": "https://www.tiktok.com/@francewtf/video/placeholder9"},
        {"url": "https://www.tiktok.com/@francewtf/video/placeholder10"},
        {"url": "https://www.tiktok.com/@francewtf/video/placeholder11"},
        {"url": "https://www.tiktok.com/@francewtf/video/placeholder12"},
        {"url": "https://www.tiktok.com/@francewtf/video/placeholder13"}
      ],
      "germany": [
        {"url": "https://www.tiktok.com/@germanywtf/video/placeholder1"},
        {"url": "https://www.tiktok.com/@germanywtf/video/placeholder2"},
        {"url": "https://www.tiktok.com/@germanywtf/video/placeholder3"},
        {"url": "https://www.tiktok.com/@germanywtf/video/placeholder4"},
        {"url": "https://www.tiktok.com/@germanywtf/video/placeholder5"},
        {"url": "https://www.tiktok.com/@germanywtf/video/placeholder6"},
        {"url": "https://www.tiktok.com/@germanywtf/video/placeholder7"},
        {"url": "https://www.tiktok.com/@germanywtf/video/placeholder8"},
        {"url": "https://www.tiktok.com/@germanywtf/video/placeholder9"},
        {"url": "https://www.tiktok.com/@germanywtf/video/placeholder10"},
        {"url": "https://www.tiktok.com/@germanywtf/video/placeholder11"},
        {"url": "https://www.tiktok.com/@germanywtf/video/placeholder12"},
        {"url": "https://www.tiktok.com/@germanywtf/video/placeholder13"}
      ],
      "spain": [
        {"url": "https://www.tiktok.com/@spainwtf/video/placeholder1"},
        {"url": "https://www.tiktok.com/@spainwtf/video/placeholder2"},
        {"url": "https://www.tiktok.com/@spainwtf/video/placeholder3"},
        {"url": "https://www.tiktok.com/@spainwtf/video/placeholder4"},
        {"url": "https://www.tiktok.com/@spainwtf/video/placeholder5"},
        {"url": "https://www.tiktok.com/@spainwtf/video/placeholder6"},
        {"url": "https://www.tiktok.com/@spainwtf/video/placeholder7"},
        {"url": "https://www.tiktok.com/@spainwtf/video/placeholder8"},
        {"url": "https://www.tiktok.com/@spainwtf/video/placeholder9"},
        {"url": "https://www.tiktok.com/@spainwtf/video/placeholder10"},
        {"url": "https://www.tiktok.com/@spainwtf/video/placeholder11"},
        {"url": "https://www.tiktok.com/@spainwtf/video/placeholder12"},
        {"url": "https://www.tiktok.com/@spainwtf/video/placeholder13"}
      ],
      "italy": [
        {"url": "https://www.tiktok.com/@italywtf/video/placeholder1"},
        {"url": "https://www.tiktok.com/@italywtf/video/placeholder2"},
        {"url": "https://www.tiktok.com/@italywtf/video/placeholder3"},
        {"url": "https://www.tiktok.com/@italywtf/video/placeholder4"},
        {"url": "https://www.tiktok.com/@italywtf/video/placeholder5"},
        {"url": "https://www.tiktok.com/@italywtf/video/placeholder6"},
        {"url": "https://www.tiktok.com/@italywtf/video/placeholder7"},
        {"url": "https://www.tiktok.com/@italywtf/video/placeholder8"},
        {"url": "https://www.tiktok.com/@italywtf/video/placeholder9"},
        {"url": "https://www.tiktok.com/@italywtf/video/placeholder10"},
        {"url": "https://www.tiktok.com/@italywtf/video/placeholder11"},
        {"url": "https://www.tiktok.com/@italywtf/video/placeholder12"},
        {"url": "https://www.tiktok.com/@italywtf/video/placeholder13"}
      ],
      "netherlands": [
        {"url": "https://www.tiktok.com/@netherlandswtf/video/placeholder1"},
        {"url": "https://www.tiktok.com/@netherlandswtf/video/placeholder2"},
        {"url": "https://www.tiktok.com/@netherlandswtf/video/placeholder3"},
        {"url": "https://www.tiktok.com/@netherlandswtf/video/placeholder4"},
        {"url": "https://www.tiktok.com/@netherlandswtf/video/placeholder5"},
        {"url": "https://www.tiktok.com/@netherlandswtf/video/placeholder6"},
        {"url": "https://www.tiktok.com/@netherlandswtf/video/placeholder7"},
        {"url": "https://www.tiktok.com/@netherlandswtf/video/placeholder8"},
        {"url": "https://www.tiktok.com/@netherlandswtf/video/placeholder9"},
        {"url": "https://www.tiktok.com/@netherlandswtf/video/placeholder10"},
        {"url": "https://www.tiktok.com/@netherlandswtf/video/placeholder11"},
        {"url": "https://www.tiktok.com/@netherlandswtf/video/placeholder12"},
        {"url": "https://www.tiktok.com/@netherlandswtf/video/placeholder13"}
      ],
      "poland": [
        {"url": "https://www.tiktok.com/@polandwtf/video/placeholder1"},
        {"url": "https://www.tiktok.com/@polandwtf/video/placeholder2"},
        {"url": "https://www.tiktok.com/@polandwtf/video/placeholder3"},
        {"url": "https://www.tiktok.com/@polandwtf/video/placeholder4"},
        {"url": "https://www.tiktok.com/@polandwtf/video/placeholder5"},
        {"url": "https://www.tiktok.com/@polandwtf/video/placeholder6"},
        {"url": "https://www.tiktok.com/@polandwtf/video/placeholder7"},
        {"url": "https://www.tiktok.com/@polandwtf/video/placeholder8"},
        {"url": "https://www.tiktok.com/@polandwtf/video/placeholder9"},
        {"url": "https://www.tiktok.com/@polandwtf/video/placeholder10"},
        {"url": "https://www.tiktok.com/@polandwtf/video/placeholder11"},
        {"url": "https://www.tiktok.com/@polandwtf/video/placeholder12"},
        {"url": "https://www.tiktok.com/@polandwtf/video/placeholder13"}
      ],
      "sweden": [
        {"url": "https://www.tiktok.com/@swedenwtf/video/placeholder1"},
        {"url": "https://www.tiktok.com/@swedenwtf/video/placeholder2"},
        {"url": "https://www.tiktok.com/@swedenwtf/video/placeholder3"},
        {"url": "https://www.tiktok.com/@swedenwtf/video/placeholder4"},
        {"url": "https://www.tiktok.com/@swedenwtf/video/placeholder5"},
        {"url": "https://www.tiktok.com/@swedenwtf/video/placeholder6"},
        {"url": "https://www.tiktok.com/@swedenwtf/video/placeholder7"},
        {"url": "https://www.tiktok.com/@swedenwtf/video/placeholder8"},
        {"url": "https://www.tiktok.com/@swedenwtf/video/placeholder9"},
        {"url": "https://www.tiktok.com/@swedenwtf/video/placeholder10"},
        {"url": "https://www.tiktok.com/@swedenwtf/video/placeholder11"},
        {"url": "https://www.tiktok.com/@swedenwtf/video/placeholder12"},
        {"url": "https://www.tiktok.com/@swedenwtf/video/placeholder13"}
      ],
      "usamerica": [
        {"url": "https://www.tiktok.com/@usa_wtf/video/placeholder1"},
        {"url": "https://www.tiktok.com/@usa_wtf/video/placeholder2"},
        {"url": "https://www.tiktok.com/@usa_wtf/video/placeholder3"},
        {"url": "https://www.tiktok.com/@usa_wtf/video/placeholder4"},
        {"url": "https://www.tiktok.com/@usa_wtf/video/placeholder5"},
        {"url": "https://www.tiktok.com/@usa_wtf/video/placeholder6"},
        {"url": "https://www.tiktok.com/@usa_wtf/video/placeholder7"},
        {"url": "https://www.tiktok.com/@usa_wtf/video/placeholder8"},
        {"url": "https://www.tiktok.com/@usa_wtf/video/placeholder9"},
        {"url": "https://www.tiktok.com/@usa_wtf/video/placeholder10"},
        {"url": "https://www.tiktok.com/@usa_wtf/video/placeholder11"},
        {"url": "https://www.tiktok.com/@usa_wtf/video/placeholder12"},
        {"url": "https://www.tiktok.com/@usa_wtf/video/placeholder13"}
      ],
      "canada": [
        {"url": "https://www.tiktok.com/@canadawtf/video/placeholder1"},
        {"url": "https://www.tiktok.com/@canadawtf/video/placeholder2"},
        {"url": "https://www.tiktok.com/@canadawtf/video/placeholder3"},
        {"url": "https://www.tiktok.com/@canadawtf/video/placeholder4"},
        {"url": "https://www.tiktok.com/@canadawtf/video/placeholder5"},
        {"url": "https://www.tiktok.com/@canadawtf/video/placeholder6"},
        {"url": "https://www.tiktok.com/@canadawtf/video/placeholder7"},
        {"url": "https://www.tiktok.com/@canadawtf/video/placeholder8"},
        {"url": "https://www.tiktok.com/@canadawtf/video/placeholder9"},
        {"url": "https://www.tiktok.com/@canadawtf/video/placeholder10"},
        {"url": "https://www.tiktok.com/@canadawtf/video/placeholder11"},
        {"url": "https://www.tiktok.com/@canadawtf/video/placeholder12"},
        {"url": "https://www.tiktok.com/@canadawtf/video/placeholder13"}
      ],
      "australia": [
        {"url": "https://www.tiktok.com/@australiawtf/video/placeholder1"},
        {"url": "https://www.tiktok.com/@australiawtf/video/placeholder2"},
        {"url": "https://www.tiktok.com/@australiawtf/video/placeholder3"},
        {"url": "https://www.tiktok.com/@australiawtf/video/placeholder4"},
        {"url": "https://www.tiktok.com/@australiawtf/video/placeholder5"},
        {"url": "https://www.tiktok.com/@australiawtf/video/placeholder6"},
        {"url": "https://www.tiktok.com/@australiawtf/video/placeholder7"},
        {"url": "https://www.tiktok.com/@australiawtf/video/placeholder8"},
        {"url": "https://www.tiktok.com/@australiawtf/video/placeholder9"},
        {"url": "https://www.tiktok.com/@australiawtf/video/placeholder10"},
        {"url": "https://www.tiktok.com/@australiawtf/video/placeholder11"},
        {"url": "https://www.tiktok.com/@australiawtf/video/placeholder12"},
        {"url": "https://www.tiktok.com/@australiawtf/video/placeholder13"}
      ]
    }
  },
  "instagram": {
    "reels": [],
    "ad_positions": [6, 9],
    "regional": {
      "scotland": [
        {"url": "https://www.instagram.com/reel/placeholder1/"},
        {"url": "https://www.instagram.com/reel/placeholder2/"},
        {"url": "https://www.instagram.com/reel/placeholder3/"},
        {"url": "https://www.instagram.com/reel/placeholder4/"},
        {"url": "https://www.instagram.com/reel/placeholder5/"},
        {"url": "https://www.instagram.com/reel/placeholder6/"},
        {"url": "https://www.instagram.com/reel/placeholder7/"},
        {"url": "https://www.instagram.com/reel/placeholder8/"},
        {"url": "https://www.instagram.com/reel/placeholder9/"},
        {"url": "https://www.instagram.com/reel/placeholder10/"},
        {"url": "https://www.instagram.com/reel/placeholder11/"},
        {"url": "https://www.instagram.com/reel/placeholder12/"},
        {"url": "https://www.instagram.com/reel/placeholder13/"}
      ],
      "britain": [
        {"url": "https://www.instagram.com/reel/britain_placeholder1/"},
        {"url": "https://www.instagram.com/reel/britain_placeholder2/"},
        {"url": "https://www.instagram.com/reel/britain_placeholder3/"},
        {"url": "https://www.instagram.com/reel/britain_placeholder4/"},
        {"url": "https://www.instagram.com/reel/britain_placeholder5/"},
        {"url": "https://www.instagram.com/reel/britain_placeholder6/"},
        {"url": "https://www.instagram.com/reel/britain_placeholder7/"},
        {"url": "https://www.instagram.com/reel/britain_placeholder8/"},
        {"url": "https://www.instagram.com/reel/britain_placeholder9/"},
        {"url": "https://www.instagram.com/reel/britain_placeholder10/"},
        {"url": "https://www.instagram.com/reel/britain_placeholder11/"},
        {"url": "https://www.instagram.com/reel/britain_placeholder12/"},
        {"url": "https://www.instagram.com/reel/britain_placeholder13/"}
      ],
      "ai": [
        {"url": "https://www.instagram.com/reel/ai_placeholder1/"},
        {"url": "https://www.instagram.com/reel/ai_placeholder2/"},
        {"url": "https://www.instagram.com/reel/ai_placeholder3/"},
        {"url": "https://www.instagram.com/reel/ai_placeholder4/"},
        {"url": "https://www.instagram.com/reel/ai_placeholder5/"},
        {"url": "https://www.instagram.com/reel/ai_placeholder6/"},
        {"url": "https://www.instagram.com/reel/ai_placeholder7/"},
        {"url": "https://www.instagram.com/reel/ai_placeholder8/"},
        {"url": "https://www.instagram.com/reel/ai_placeholder9/"},
        {"url": "https://www.instagram.com/reel/ai_placeholder10/"},
        {"url": "https://www.instagram.com/reel/ai_placeholder11/"},
        {"url": "https://www.instagram.com/reel/ai_placeholder12/"},
        {"url": "https://www.instagram.com/reel/ai_placeholder13/"}
      ],
      "europe": [
        {"url": "https://www.instagram.com/reel/europe_placeholder1/"},
        {"url": "https://www.instagram.com/reel/europe_placeholder2/"},
        {"url": "https://www.instagram.com/reel/europe_placeholder3/"},
        {"url": "https://www.instagram.com/reel/europe_placeholder4/"},
        {"url": "https://www.instagram.com/reel/europe_placeholder5/"},
        {"url": "https://www.instagram.com/reel/europe_placeholder6/"},
        {"url": "https://www.instagram.com/reel/europe_placeholder7/"},
        {"url": "https://www.instagram.com/reel/europe_placeholder8/"},
        {"url": "https://www.instagram.com/reel/europe_placeholder9/"},
        {"url": "https://www.instagram.com/reel/europe_placeholder10/"},
        {"url": "https://www.instagram.com/reel/europe_placeholder11/"},
        {"url": "https://www.instagram.com/reel/europe_placeholder12/"},
        {"url": "https://www.instagram.com/reel/europe_placeholder13/"}
      ],
      "england": [
        {"url": "https://www.instagram.com/reel/england_placeholder1/"},
        {"url": "https://www.instagram.com/reel/england_placeholder2/"},
        {"url": "https://www.instagram.com/reel/england_placeholder3/"},
        {"url": "https://www.instagram.com/reel/england_placeholder4/"},
        {"url": "https://www.instagram.com/reel/england_placeholder5/"},
        {"url": "https://www.instagram.com/reel/england_placeholder6/"},
        {"url": "https://www.instagram.com/reel/england_placeholder7/"},
        {"url": "https://www.instagram.com/reel/england_placeholder8/"},
        {"url": "https://www.instagram.com/reel/england_placeholder9/"},
        {"url": "https://www.instagram.com/reel/england_placeholder10/"},
        {"url": "https://www.instagram.com/reel/england_placeholder11/"},
        {"url": "https://www.instagram.com/reel/england_placeholder12/"},
        {"url": "https://www.instagram.com/reel/england_placeholder13/"}
      ],
      "wales": [
        {"url": "https://www.instagram.com/reel/wales_placeholder1/"},
        {"url": "https://www.instagram.com/reel/wales_placeholder2/"},
        {"url": "https://www.instagram.com/reel/wales_placeholder3/"},
        {"url": "https://www.instagram.com/reel/wales_placeholder4/"},
        {"url": "https://www.instagram.com/reel/wales_placeholder5/"},
        {"url": "https://www.instagram.com/reel/wales_placeholder6/"},
        {"url": "https://www.instagram.com/reel/wales_placeholder7/"},
        {"url": "https://www.instagram.com/reel/wales_placeholder8/"},
        {"url": "https://www.instagram.com/reel/wales_placeholder9/"},
        {"url": "https://www.instagram.com/reel/wales_placeholder10/"},
        {"url": "https://www.instagram.com/reel/wales_placeholder11/"},
        {"url": "https://www.instagram.com/reel/wales_placeholder12/"},
        {"url": "https://www.instagram.com/reel/wales_placeholder13/"}
      ],
      "ireland": [
        {"url": "https://www.instagram.com/reel/ireland_placeholder1/"},
        {"url": "https://www.instagram.com/reel/ireland_placeholder2/"},
        {"url": "https://www.instagram.com/reel/ireland_placeholder3/"},
        {"url": "https://www.instagram.com/reel/ireland_placeholder4/"},
        {"url": "https://www.instagram.com/reel/ireland_placeholder5/"},
        {"url": "https://www.instagram.com/reel/ireland_placeholder6/"},
        {"url": "https://www.instagram.com/reel/ireland_placeholder7/"},
        {"url": "https://www.instagram.com/reel/ireland_placeholder8/"},
        {"url": "https://www.instagram.com/reel/ireland_placeholder9/"},
        {"url": "https://www.instagram.com/reel/ireland_placeholder10/"},
        {"url": "https://www.instagram.com/reel/ireland_placeholder11/"},
        {"url": "https://www.instagram.com/reel/ireland_placeholder12/"},
        {"url": "https://www.instagram.com/reel/ireland_placeholder13/"}
      ],
      "france": [
        {"url": "https://www.instagram.com/reel/france_placeholder1/"},
        {"url": "https://www.instagram.com/reel/france_placeholder2/"},
        {"url": "https://www.instagram.com/reel/france_placeholder3/"},
        {"url": "https://www.instagram.com/reel/france_placeholder4/"},
        {"url": "https://www.instagram.com/reel/france_placeholder5/"},
        {"url": "https://www.instagram.com/reel/france_placeholder6/"},
        {"url": "https://www.instagram.com/reel/france_placeholder7/"},
        {"url": "https://www.instagram.com/reel/france_placeholder8/"},
        {"url": "https://www.instagram.com/reel/france_placeholder9/"},
        {"url": "https://www.instagram.com/reel/france_placeholder10/"},
        {"url": "https://www.instagram.com/reel/france_placeholder11/"},
        {"url": "https://www.instagram.com/reel/france_placeholder12/"},
        {"url": "https://www.instagram.com/reel/france_placeholder13/"}
      ],
      "germany": [
        {"url": "https://www.instagram.com/reel/germany_placeholder1/"},
        {"url": "https://www.instagram.com/reel/germany_placeholder2/"},
        {"url": "https://www.instagram.com/reel/germany_placeholder3/"},
        {"url": "https://www.instagram.com/reel/germany_placeholder4/"},
        {"url": "https://www.instagram.com/reel/germany_placeholder5/"},
        {"url": "https://www.instagram.com/reel/germany_placeholder6/"},
        {"url": "https://www.instagram.com/reel/germany_placeholder7/"},
        {"url": "https://www.instagram.com/reel/germany_placeholder8/"},
        {"url": "https://www.instagram.com/reel/germany_placeholder9/"},
        {"url": "https://www.instagram.com/reel/germany_placeholder10/"},
        {"url": "https://www.instagram.com/reel/germany_placeholder11/"},
        {"url": "https://www.instagram.com/reel/germany_placeholder12/"},
        {"url": "https://www.instagram.com/reel/germany_placeholder13/"}
      ],
      "spain": [
        {"url": "https://www.instagram.com/reel/spain_placeholder1/"},
        {"url": "https://www.instagram.com/reel/spain_placeholder2/"},
        {"url": "https://www.instagram.com/reel/spain_placeholder3/"},
        {"url": "https://www.instagram.com/reel/spain_placeholder4/"},
        {"url": "https://www.instagram.com/reel/spain_placeholder5/"},
        {"url": "https://www.instagram.com/reel/spain_placeholder6/"},
        {"url": "https://www.instagram.com/reel/spain_placeholder7/"},
        {"url": "https://www.instagram.com/reel/spain_placeholder8/"},
        {"url": "https://www.instagram.com/reel/spain_placeholder9/"},
        {"url": "https://www.instagram.com/reel/spain_placeholder10/"},
        {"url": "https://www.instagram.com/reel/spain_placeholder11/"},
        {"url": "https://www.instagram.com/reel/spain_placeholder12/"},
        {"url": "https://www.instagram.com/reel/spain_placeholder13/"}
      ],
      "italy": [
        {"url": "https://www.instagram.com/reel/italy_placeholder1/"},
        {"url": "https://www.instagram.com/reel/italy_placeholder2/"},
        {"url": "https://www.instagram.com/reel/italy_placeholder3/"},
        {"url": "https://www.instagram.com/reel/italy_placeholder4/"},
        {"url": "https://www.instagram.com/reel/italy_placeholder5/"},
        {"url": "https://www.instagram.com/reel/italy_placeholder6/"},
        {"url": "https://www.instagram.com/reel/italy_placeholder7/"},
        {"url": "https://www.instagram.com/reel/italy_placeholder8/"},
        {"url": "https://www.instagram.com/reel/italy_placeholder9/"},
        {"url": "https://www.instagram.com/reel/italy_placeholder10/"},
        {"url": "https://www.instagram.com/reel/italy_placeholder11/"},
        {"url": "https://www.instagram.com/reel/italy_placeholder12/"},
        {"url": "https://www.instagram.com/reel/italy_placeholder13/"}
      ],
      "netherlands": [
        {"url": "https://www.instagram.com/reel/netherlands_placeholder1/"},
        {"url": "https://www.instagram.com/reel/netherlands_placeholder2/"},
        {"url": "https://www.instagram.com/reel/netherlands_placeholder3/"},
        {"url": "https://www.instagram.com/reel/netherlands_placeholder4/"},
        {"url": "https://www.instagram.com/reel/netherlands_placeholder5/"},
        {"url": "https://www.instagram.com/reel/netherlands_placeholder6/"},
        {"url": "https://www.instagram.com/reel/netherlands_placeholder7/"},
        {"url": "https://www.instagram.com/reel/netherlands_placeholder8/"},
        {"url": "https://www.instagram.com/reel/netherlands_placeholder9/"},
        {"url": "https://www.instagram.com/reel/netherlands_placeholder10/"},
        {"url": "https://www.instagram.com/reel/netherlands_placeholder11/"},
        {"url": "https://www.instagram.com/reel/netherlands_placeholder12/"},
        {"url": "https://www.instagram.com/reel/netherlands_placeholder13/"}
      ],
      "poland": [
        {"url": "https://www.instagram.com/reel/poland_placeholder1/"},
        {"url": "https://www.instagram.com/reel/poland_placeholder2/"},
        {"url": "https://www.instagram.com/reel/poland_placeholder3/"},
        {"url": "https://www.instagram.com/reel/poland_placeholder4/"},
        {"url": "https://www.instagram.com/reel/poland_placeholder5/"},
        {"url": "https://www.instagram.com/reel/poland_placeholder6/"},
        {"url": "https://www.instagram.com/reel/poland_placeholder7/"},
        {"url": "https://www.instagram.com/reel/poland_placeholder8/"},
        {"url": "https://www.instagram.com/reel/poland_placeholder9/"},
        {"url": "https://www.instagram.com/reel/poland_placeholder10/"},
        {"url": "https://www.instagram.com/reel/poland_placeholder11/"},
        {"url": "https://www.instagram.com/reel/poland_placeholder12/"},
        {"url": "https://www.instagram.com/reel/poland_placeholder13/"}
      ],
      "sweden": [
        {"url": "https://www.instagram.com/reel/sweden_placeholder1/"},
        {"url": "https://www.instagram.com/reel/sweden_placeholder2/"},
        {"url": "https://www.instagram.com/reel/sweden_placeholder3/"},
        {"url": "https://www.instagram.com/reel/sweden_placeholder4/"},
        {"url": "https://www.instagram.com/reel/sweden_placeholder5/"},
        {"url": "https://www.instagram.com/reel/sweden_placeholder6/"},
        {"url": "https://www.instagram.com/reel/sweden_placeholder7/"},
        {"url": "https://www.instagram.com/reel/sweden_placeholder8/"},
        {"url": "https://www.instagram.com/reel/sweden_placeholder9/"},
        {"url": "https://www.instagram.com/reel/sweden_placeholder10/"},
        {"url": "https://www.instagram.com/reel/sweden_placeholder11/"},
        {"url": "https://www.instagram.com/reel/sweden_placeholder12/"},
        {"url": "https://www.instagram.com/reel/sweden_placeholder13/"}
      ],
      "usamerica": [
        {"url": "https://www.instagram.com/reel/usa_placeholder1/"},
        {"url": "https://www.instagram.com/reel/usa_placeholder2/"},
        {"url": "https://www.instagram.com/reel/usa_placeholder3/"},
        {"url": "https://www.instagram.com/reel/usa_placeholder4/"},
        {"url": "https://www.instagram.com/reel/usa_placeholder5/"},
        {"url": "https://www.instagram.com/reel/usa_placeholder6/"},
        {"url": "https://www.instagram.com/reel/usa_placeholder7/"},
        {"url": "https://www.instagram.com/reel/usa_placeholder8/"},
        {"url": "https://www.instagram.com/reel/usa_placeholder9/"},
        {"url": "https://www.instagram.com/reel/usa_placeholder10/"},
        {"url": "https://www.instagram.com/reel/usa_placeholder11/"},
        {"url": "https://www.instagram.com/reel/usa_placeholder12/"},
        {"url": "https://www.instagram.com/reel/usa_placeholder13/"}
      ],
      "canada": [
        {"url": "https://www.instagram.com/reel/canada_placeholder1/"},
        {"url": "https://www.instagram.com/reel/canada_placeholder2/"},
        {"url": "https://www.instagram.com/reel/canada_placeholder3/"},
        {"url": "https://www.instagram.com/reel/canada_placeholder4/"},
        {"url": "https://www.instagram.com/reel/canada_placeholder5/"},
        {"url": "https://www.instagram.com/reel/canada_placeholder6/"},
        {"url": "https://www.instagram.com/reel/canada_placeholder7/"},
        {"url": "https://www.instagram.com/reel/canada_placeholder8/"},
        {"url": "https://www.instagram.com/reel/canada_placeholder9/"},
        {"url": "https://www.instagram.com/reel/canada_placeholder10/"},
        {"url": "https://www.instagram.com/reel/canada_placeholder11/"},
        {"url": "https://www.instagram.com/reel/canada_placeholder12/"},
        {"url": "https://www.instagram.com/reel/canada_placeholder13/"}
      ],
      "australia": [
        {"url": "https://www.instagram.com/reel/australia_placeholder1/"},
        {"url": "https://www.instagram.com/reel/australia_placeholder2/"},
        {"url": "https://www.instagram.com/reel/australia_placeholder3/"},
        {"url": "https://www.instagram.com/reel/australia_placeholder4/"},
        {"url": "https://www.instagram.com/reel/australia_placeholder5/"},
        {"url": "https://www.instagram.com/reel/australia_placeholder6/"},
        {"url": "https://www.instagram.com/reel/australia_placeholder7/"},
        {"url": "https://www.instagram.com/reel/australia_placeholder8/"},
        {"url": "https://www.instagram.com/reel/australia_placeholder9/"},
        {"url": "https://www.instagram.com/reel/australia_placeholder10/"},
        {"url": "https://www.instagram.com/reel/australia_placeholder11/"},
        {"url": "https://www.instagram.com/reel/australia_placeholder12/"},
        {"url": "https://www.instagram.com/reel/australia_placeholder13/"}
      ]
    }
  },
  "youtube": {
    "videos": [],
    "limit": 5
  },
  "x": {
    "posts": [],
    "limit": 3
  },
  "threads": {
    "posts": [],
    "limit": 3
  }
}
